MkAuth/__init__.py
MkAuth-0.0.42.dist-info/LICENSE
MkAuth-0.0.42.dist-info/METADATA
MkAuth-0.0.42.dist-info/WHEEL
MkAuth-0.0.42.dist-info/top_level.txt
MkAuth-0.0.42.dist-info/RECORD
