Metadata-Version: 2.1
Name: MkAuth
Version: 0.0.42
Summary: MkNxGn User Management. Free for use.
Home-page: https://mknxgn.com/
Author: Mark Cartagena
Author-email: mark@mknxgn.com
License: UNKNOWN
Platform: UNKNOWN
Classifier: Programming Language :: Python :: 3
Classifier: License :: OSI Approved :: MIT License
Classifier: Operating System :: OS Independent
Requires: mknxgn_essentials
Requires: flask
License-File: LICENSE
